gitmon
