Metadata-Version: 1.1
Name: GitMon
Version: 0.3.4
Summary: GitMon - The Git Repository Monitor
Home-page: http://github.com/spajus/gitmon/
Author: Tomas Varaneckas
Author-email: tomas.varaneckas@gmail.com
License: GPLv3
Keywords: git,monitor,scm,repository
Platform: UNKNOWN
Classifier: Development Status :: 4 - Beta
Classifier: Environment :: MacOS X
Classifier: License :: OSI Approved :: GNU General Public License (GPL)
Classifier: Operating System :: OS Independent
Classifier: Programming Language :: Python
Classifier: Topic :: Utilities
Requires: gitpython (>=0.2.9)
Requires: py_Growl_2_6 (>=0.0.7)
